core/__init__.py
core/apps.py
core/validator.py
core/context_processors/__init__.py
core/context_processors/jwt_token.py
core/context_processors/sidebar_color.py
core/management/__init__.py
core/management/commands/__init__.py
core/management/commands/appmigrations.py
core/management/commands/newapi.py
core/management/commands/newapp.py
core/management/commands/setup.py
core/management/commands/staffuser.py
core/management/commands/superuser.py
core/migrations/__init__.py
rakib_django_core-0.1.2.dist-info/LICENSE
rakib_django_core-0.1.2.dist-info/METADATA
rakib_django_core-0.1.2.dist-info/WHEEL
rakib_django_core-0.1.2.dist-info/top_level.txt
rakib_django_core-0.1.2.dist-info/RECORD
