Metadata-Version: 2.1
Name: rakib-django-core
Version: 0.1.2
Summary: This is a Django-based web application for managing core functionalities.
Home-page: https://github.com/rakib1515hassan/django-core-app
Author: Md. Rakib Hassan
Author-email: "Md. Rakib Hassan" <rakib1515hassan@gmail.com>
Project-URL: Homepage, https://github.com/rakib1515hassan/django-core-app
Classifier: Development Status :: 3 - Alpha
Classifier: Intended Audience :: Developers
Classifier: License :: OSI Approved :: MIT License
Classifier: Operating System :: OS Independent
Classifier: Programming Language :: Python :: 3
Classifier: Programming Language :: Python :: 3.7
Classifier: Programming Language :: Python :: 3.8
Classifier: Programming Language :: Python :: 3.9
Classifier: Programming Language :: Python :: 3.10
Classifier: Framework :: Django
Classifier: Framework :: Django :: 3.2
Classifier: Framework :: Django :: 4.0
Requires-Python: >=3.7
License-File: LICENSE
Requires-Dist: Django>=3.2
